[
    {
        "ge_lyu_str": "中平中仄中仄中平仄中平中中平仄中仄中平仄中仄平平仄仄中仄平平仄中平平仄中平中仄中仄中平仄平仄仄仄平平平仄中仄平平仄中仄中仄平平仄仄平中仄中仄平平仄仄中仄平平仄中平平仄中平中仄中仄中平仄平仄",
        "rhyme_pos": [
            8,
            19,
            30,
            34,
            45,
            56,
            67,
            78,
            82,
            93
        ],
        "yun_classify": {
            "0": [
                8,
                19,
                30,
                34,
                45,
                56,
                67,
                78,
                82,
                93
            ]
        },
        "ci_sep": [
            "澹烟残照　摇曳溪光碧",
            "溪边浅桃深杏　迤逦染春色",
            "昨夜扁舟泊处　枕簟当滩碛",
            "波声渔笛",
            "惊回好梦　梦里欲归怎归得",
            "辗转翻成无寐　因此伤行役",
            "思念多媚多娇　咫尺千里隔",
            "都为深情密爱　不忍轻离拆",
            "好天良夕",
            "鸳帏寂静　算得也应暗思忆"
        ],
        "ge_lyu_sep": [
            "中平中仄句中仄中平仄韵",
            "中平中中平仄句中仄中平仄韵",
            "中仄平平仄仄句中仄平平仄韵",
            "中平平仄韵",
            "中平中仄句中仄中平仄平仄韵",
            "仄仄平平平仄句中仄平平仄韵",
            "中仄中仄平平句仄仄平中仄韵",
            "中仄平平仄仄句中仄平平仄韵",
            "中平平仄韵",
            "中平中仄句中仄中平仄平仄韵"
        ],
        "origin": "澹烟残照，摇曳溪光碧。溪边浅桃深杏，迤逦染春色。昨夜扁舟泊处，枕簟当滩碛。波声渔笛。惊回好梦，梦里欲归怎归得。辗转翻成无寐，因此伤行役。思念多媚多娇，咫尺千里隔。都为深情密爱，不忍轻离拆。好天良夕。鸳帏寂静，算得也应暗思忆。",
        "origin_trad": "澹煙殘照，搖曳溪光碧。溪邊淺桃深杏，迤邐染春色。昨夜扁舟泊處，枕簟當灘磧。波聲漁笛。驚回好夢，夢裏欲歸怎歸得。輾轉翻成無寐，因此傷行役。思念多媚多嬌，咫尺千里隔。都為深情密愛，不忍輕離拆。好天良夕。鴛幃寂靜，算得也應暗思憶。"
    },
    {
        "ge_lyu_str": "仄平平仄平仄仄平仄平平仄仄仄仄仄仄平平仄平仄平平仄仄仄仄平平仄平平平仄平平仄仄平仄平平仄平仄平仄平平仄仄仄仄平平仄平仄平仄平平仄仄平平仄平仄平平仄仄平仄平平仄平平平仄仄平平仄平仄平平仄平仄",
        "rhyme_pos": [
            8,
            19,
            25,
            30,
            34,
            45,
            51,
            56,
            67,
            73,
            78,
            82,
            93
        ],
        "yun_classify": {
            "0": [
                8,
                19,
                25,
                30,
                34,
                45,
                51,
                56,
                67,
                73,
                78,
                82,
                93
            ]
        },
        "ci_sep": [
            "暮云消散　帘卷画堂晓",
            "残薰烬蜡隐映　绮席金壶倒",
            "尘送行鞭袅袅",
            "醉指长安道",
            "波平天杳",
            "兰舟欲上　回首离愁满芳草",
            "身外浮名扰扰",
            "已负狂年少",
            "无奈风月多情　此去应相笑",
            "心记歌声缥缈",
            "翻是相思调",
            "明年春早",
            "宛溪杨柳　依旧青青为谁好"
        ],
        "ge_lyu_sep": [
            "仄平平仄句平仄仄平仄韵",
            "平平仄仄仄仄句仄仄平平仄韵",
            "平仄平平仄仄韵",
            "仄仄平平仄韵",
            "平平平仄韵",
            "平平仄仄句平仄平平仄平仄韵",
            "平仄平平仄仄韵",
            "仄仄平平仄韵",
            "平仄平仄平平句仄仄平平仄韵",
            "平仄平平仄仄韵",
            "平仄平平仄韵",
            "平平平仄韵",
            "仄平平仄句平仄平平仄平仄韵"
        ],
        "origin": "暮云消散，帘卷画堂晓。残薰烬蜡隐映，绮席金壶倒。尘送行鞭袅袅。醉指长安道。波平天杳。兰舟欲上，回首离愁满芳草。身外浮名扰扰。已负狂年少。无奈风月多情，此去应相笑。心记歌声缥缈。翻是相思调。明年春早。宛溪杨柳，依旧青青为谁好。",
        "origin_trad": "暮雲消散，簾卷畫堂曉。殘薰燼蠟隱映，綺席金壺倒。塵送行鞭裊裊。醉指長安道。波平天杳。蘭舟欲上，回首離愁滿芳草。身外浮名擾擾。已負狂年少。無奈風月多情，此去應相笑。心記歌聲縹緲。翻是相思調。明年春早。宛溪楊柳，依舊青青為誰好。"
    },
    {
        "ge_lyu_str": "仄平平仄平仄仄平仄平平仄平平仄仄仄平平仄平仄平平仄仄仄仄平平仄仄平平仄平平仄仄平仄平平仄平仄仄平平仄仄仄仄仄平平仄平仄仄仄平平仄仄平平仄平仄平平仄仄仄仄平平仄平平平仄平平平仄仄仄平平仄平仄",
        "rhyme_pos": [
            8,
            19,
            30,
            34,
            45,
            56,
            67,
            78,
            82,
            93
        ],
        "yun_classify": {
            "0": [
                8,
                19,
                30,
                34,
                45,
                56,
                67,
                78,
                82,
                93
            ]
        },
        "ci_sep": [
            "授衣时节　犹未定寒燠",
            "长空雨收云霁　湛碧秋容沐",
            "还是鲈肥蟹美　橡粟村村熟",
            "不堪追逐",
            "龙山梦远　惆怅田园自黄菊",
            "醉中还念倦旅　触景伤心目",
            "羞破帽　把茱萸　更忆尊前玉",
            "愁立梧桐影下　月转回廊曲",
            "归期将卜",
            "西风吹雁　懒寄斜封但相嘱"
        ],
        "ge_lyu_sep": [
            "仄平平仄句平仄仄平仄韵",
            "平平仄平平仄句仄仄平平仄韵",
            "平仄平平仄仄句仄仄平平仄韵",
            "仄平平仄韵",
            "平平仄仄句平仄平平仄平仄韵",
            "仄平平仄仄仄句仄仄平平仄韵",
            "平仄仄读仄平平句仄仄平平仄韵",
            "平仄平平仄仄句仄仄平平仄韵",
            "平平平仄韵",
            "平平平仄句仄仄平平仄平仄韵"
        ],
        "origin": "授衣时节，犹未定寒燠。长空雨收云霁，湛碧秋容沐。还是鲈肥蟹美，橡粟村村熟。不堪追逐。龙山梦远，惆怅田园自黄菊。醉中还念倦旅，触景伤心目。羞破帽、把茱萸，更忆尊前玉。愁立梧桐影下，月转回廊曲。归期将卜。西风吹雁，懒寄斜封但相嘱。",
        "origin_trad": "授衣時節，猶未定寒燠。長空雨收雲霽，湛碧秋容沐。還是鱸肥蟹美，橡粟邨邨熟。不堪追逐。龍山夢遠，惆悵田園自黃菊。醉中還念倦旅，觸景傷心目。羞破帽、把茱萸，更憶尊前玉。愁立梧桐影下，月轉回廊曲。歸期將卜。西風吹雁，懶寄斜封但相囑。"
    }
]