[
    {
        "ge_lyu_str": "平仄平平仄平仄仄仄仄仄仄平平仄仄平平平平平仄平平仄平平平平仄平仄平平仄仄仄平仄平平仄平平仄仄平平平仄仄仄平平平仄仄仄平平仄仄平平平平平仄平平仄平平平仄仄仄仄平平仄平仄仄仄平平仄仄仄仄仄平平",
        "rhyme_pos": [
            13,
            17,
            23,
            26,
            33,
            47,
            53,
            59,
            63,
            69,
            72,
            79,
            93
        ],
        "yun_classify": {
            "0": [
                13,
                17,
                23,
                26,
                33,
                47,
                53,
                59,
                63,
                69,
                72,
                79,
                93
            ]
        },
        "ci_sep": [
            "轻霭浮空　乱峰倒影　潋滟十里银塘",
            "绕岸垂杨",
            "红楼朱阁相望",
            "芰荷香",
            "双双戏　鸂鶒鸳鸯",
            "乍雨过　兰芷汀洲　望中依约似潇湘",
            "风淡淡　水茫茫",
            "摇动一片晴光",
            "画舫相将",
            "盈盈红粉清商",
            "紫薇郎",
            "修禊饮　且乐仙乡",
            "便归去　遍历銮坡凤沼　此景也难忘"
        ],
        "ge_lyu_sep": [
            "平仄平平句仄平仄仄句仄仄仄仄平平韵",
            "仄仄平平韵",
            "平平平仄平平韵",
            "仄平平韵",
            "平平仄读平仄平平韵",
            "仄仄仄读平仄平平句仄平平仄仄平平韵",
            "平仄仄句仄平平韵",
            "平仄仄仄平平韵",
            "仄仄平平韵",
            "平平平仄平平韵",
            "仄平平韵",
            "平仄仄读仄仄平平韵",
            "仄平仄读仄仄平平仄仄句仄仄仄平平韵"
        ],
        "origin": "轻霭浮空，乱峰倒影，潋滟十里银塘。绕岸垂杨。红楼朱阁相望。芰荷香。双双戏、鸂鶒鸳鸯。乍雨过、兰芷汀洲，望中依约似潇湘。风淡淡，水茫茫。摇动一片晴光。画舫相将。盈盈红粉清商。紫薇郎。修禊饮、且乐仙乡。便归去、遍历銮坡凤沼，此景也难忘。",
        "origin_trad": "輕靄浮空，亂峰倒影，瀲灩十里銀塘。繞岸垂楊。紅樓朱閣相望。芰荷香。雙雙戲、鸂鶒鴛鴦。乍雨過、蘭芷汀洲，望中依約似瀟湘。風淡淡，水茫茫。搖動一片晴光。畫舫相將。盈盈紅粉清商。紫薇郎。修禊飲、且樂仙鄉。便歸去、遍歷鑾坡鳳沼，此景也難忘。"
    }
]