[
    {
        "ge_lyu_str": "中仄平平仄中仄中仄平平中中仄仄平平仄仄仄平平平平仄仄平平仄中仄仄仄平平中仄仄仄平平仄中仄平平平平中中仄平平中仄平中仄平平仄平仄中仄平平中仄仄平仄仄仄平平中仄平平中平仄仄仄仄平平中仄平平",
        "rhyme_pos": [
            10,
            16,
            21,
            34,
            40,
            45,
            47,
            61,
            79,
            91
        ],
        "yun_classify": {
            "0": [
                10,
                16,
                21,
                34,
                40,
                45,
                47,
                61,
                79,
                91
            ]
        },
        "ci_sep": [
            "暗叶啼风雨　窗外晓色珑璁",
            "散水麝　小池东",
            "乱一岸芙蓉",
            "蕲州簟展双纹浪　轻帐翠缕如空",
            "梦远别　泪痕重",
            "淡铅脸斜红",
            "忡忡",
            "嗟憔悴　新宽带结　羞艳冶　都销镜中",
            "有蜀纸　堪凭寄恨　等今夜　洒血书词　剪烛亲封",
            "菖蒲渐老　早晚成花　教见薰风"
        ],
        "ge_lyu_sep": [
            "中仄平平仄句中仄中仄平平韵",
            "中中仄句仄平平韵",
            "仄仄仄平平韵",
            "平平仄仄平平仄句中仄仄仄平平韵",
            "中仄仄句仄平平韵",
            "仄中仄平平韵",
            "平平韵",
            "中中仄读平平中仄句平中仄读平平仄平韵",
            "仄中仄读平平中仄句仄平仄读仄仄平平句中仄平平韵",
            "中平仄仄句仄仄平平句中仄平平韵"
        ],
        "origin": "暗叶啼风雨，窗外晓色珑璁。散水麝，小池东。乱一岸芙蓉。蕲州簟展双纹浪，轻帐翠缕如空。梦远别，泪痕重。淡铅脸斜红。忡忡。嗟憔悴、新宽带结，羞艳冶、都销镜中。有蜀纸、堪凭寄恨，等今夜、洒血书词，剪烛亲封。菖蒲渐老，早晚成花，教见薰风。",
        "origin_trad": "暗葉啼風雨，窗外曉色瓏璁。散水麝，小池東。亂一岸芙蓉。蘄州簟展雙紋浪，輕帳翠縷如空。夢遠別，淚痕重。淡鉛臉斜紅。忡忡。嗟憔悴、新寬帶結，羞豔冶、都銷鏡中。有蜀紙、堪憑寄恨，等今夜、灑血書詞，翦燭親封。菖蒲漸老，早晚成花，教見薰風。"
    }
]