[
    {
        "ge_lyu_str": "仄仄仄平平仄仄仄平平平平平仄平仄平平仄仄仄平仄仄平平平仄仄平平仄仄仄仄平平平仄仄平仄平仄平平仄平仄仄平仄平平平仄平仄仄平仄平平仄平平仄仄仄平平仄仄平平平仄仄平平仄平平平仄仄平平平仄平仄仄平仄平仄平平仄仄仄平平仄",
        "rhyme_pos": [
            13,
            18,
            27,
            38,
            51,
            66,
            71,
            80,
            91,
            104
        ],
        "yun_classify": {
            "0": [
                13,
                18,
                27,
                38,
                51,
                66,
                71,
                80,
                91,
                104
            ]
        },
        "ci_sep": [
            "远兴引游踪　漫遍踏天涯　萋萋芳草",
            "偏爱双溪好",
            "有隐侯旧迹　层楼云表",
            "碧崖丹嶂　看缥缈　凭阑吟啸",
            "偶佳遇　留捣元霜　岁星旋又周了",
            "归期谁道无据　几回首兴怀　故林猿鸟",
            "拟待春空杳",
            "与鸳俦鸿侣　共还池岛",
            "川途迢递　纵南翔　仍诉幽抱",
            "莫轻负　今日相看　但得翠尊同倒"
        ],
        "ge_lyu_sep": [
            "仄仄仄平平句仄仄仄平平句平平平仄韵",
            "平仄平平仄韵",
            "仄仄平仄仄句平平平仄韵",
            "仄平平仄句仄仄仄读平平平仄韵",
            "仄平仄读平仄平平句仄平仄仄平仄韵",
            "平平平仄平仄句仄平仄平平句仄平平仄韵",
            "仄仄平平仄韵",
            "仄平平平仄句仄平平仄韵",
            "平平平仄句仄平平读平仄平仄韵",
            "仄平仄读平仄平平句仄仄仄平平仄韵"
        ],
        "origin": "远兴引游踪，漫遍踏天涯，萋萋芳草。偏爱双溪好。有隐侯旧迹，层楼云表。碧崖丹嶂，看缥缈、凭阑吟啸。偶佳遇、留捣元霜，岁星旋又周了。归期谁道无据，几回首兴怀，故林猿鸟。拟待春空杳。与鸳俦鸿侣，共还池岛。川途迢递，纵南翔、仍诉幽抱。莫轻负、今日相看，但得翠尊同倒。",
        "origin_trad": "遠興引遊蹤，漫遍踏天涯，萋萋芳草。偏愛雙溪好。有隱侯舊跡，層樓雲表。碧崖丹嶂，看縹緲、憑闌吟嘯。偶佳遇、留擣元霜，歲星旋又周了。歸期誰道無據，幾回首興懷，故林猿鳥。擬待春空杳。與鴛儔鴻侶，共還池島。川途迢遞，縱南翔、仍訴幽抱。莫輕負、今日相看，但得翠尊同倒。"
    }
]