[
    {
        "ge_lyu_str": "仄仄平平仄平平仄平仄仄平仄平平仄仄仄仄平平仄平平平仄仄平平仄仄仄仄仄平平仄仄中仄平平仄平平仄中平仄仄平仄平平仄中平仄仄平平仄中中仄平仄平平仄仄仄仄平平仄平平平仄仄平平仄仄仄仄仄平平仄仄仄仄平平仄平平仄平平仄仄",
        "rhyme_pos": [
            12,
            25,
            30,
            37,
            51,
            57,
            66,
            79,
            91,
            103
        ],
        "yun_classify": {
            "0": [
                12,
                25,
                30,
                37,
                51,
                57,
                66,
                79,
                91,
                103
            ]
        },
        "ci_sep": [
            "露醑无情　送长歌未终　已醉离别",
            "何如暮雨　酿一襟凉润　来留佳客",
            "好山侵座碧",
            "胜昨夜　疏星淡月",
            "君欲翩然去　人间底许　员峤问帆席",
            "诗情病非畴昔",
            "赖亲朋对影　且慰良夕",
            "风流雨散　定几回肠断　能禁头白",
            "为君烦素手　剪碧藕　轻丝细雪",
            "去去江南路　犹应水云秋共色"
        ],
        "ge_lyu_sep": [
            "仄仄平平句仄平平仄平句仄仄平仄韵",
            "平平仄仄句仄仄平平仄句平平平仄韵",
            "仄平平仄仄韵",
            "仄仄仄读平平仄仄韵",
            "中仄平平仄句平平仄中句平仄仄平仄韵",
            "平平仄中平仄韵",
            "仄平平仄中句中仄平仄韵",
            "平平仄仄句仄仄平平仄句平平平仄韵",
            "仄平平仄仄句仄仄仄读平平仄仄韵",
            "仄仄平平仄句平平仄平平仄仄韵"
        ],
        "origin": "露醑无情，送长歌未终，已醉离别。何如暮雨，酿一襟凉润，来留佳客。好山侵座碧。胜昨夜、疏星淡月。君欲翩然去，人间底许，员峤问帆席。诗情病非畴昔。赖亲朋对影，且慰良夕。风流雨散，定几回肠断，能禁头白。为君烦素手，剪碧藕、轻丝细雪。去去江南路，犹应水云秋共色。",
        "origin_trad": "露醑無情，送長歌未終，已醉離別。何如暮雨，釀一襟凉潤，來留佳客。好山侵座碧。勝昨夜、疏星淡月。君欲翩然去，人間底許，員嶠問帆席。詩情病非疇昔。賴親朋對影，且慰良夕。風流雨散，定幾回腸斷，能禁頭白。為君煩素手，翦碧藕、輕絲細雪。去去江南路，猶應水雲秋共色。"
    },
    {
        "ge_lyu_str": "仄仄平平仄平平仄平平仄平仄平平仄仄仄仄平平仄平平平仄仄平平仄仄仄仄仄平平仄仄仄仄平平仄平平仄平平仄仄平仄平平仄仄平平仄平平仄平平仄平仄平平仄仄仄仄平平仄平平平仄仄平平仄仄仄仄仄平平仄仄仄仄平平仄平平仄平平仄仄",
        "rhyme_pos": [
            12,
            25,
            37,
            51,
            66,
            79,
            91,
            103
        ],
        "yun_classify": {
            "0": [
                12,
                25,
                37,
                51,
                66,
                79,
                91,
                103
            ]
        },
        "ci_sep": [
            "日色西沈　上高台　迥观天地寥廓",
            "疏星隐现　又一轮明月　昭昭无著",
            "皓然三界外　似百炼　青铜镜濯",
            "处处恩光被　家家照临　庭户起冥漠",
            "长安万里清风　助乾坤荡摇　云雾难作",
            "仙宫玉殿　正炼霞金碧　相辉参错",
            "大哉清夜景　镇万古　含弘磊落",
            "有志攀青桂　蟾宫兔边看捣药"
        ],
        "ge_lyu_sep": [
            "仄仄平平句仄平平句仄平平仄平仄韵",
            "平平仄仄句仄仄平平仄句平平平仄韵",
            "仄平平仄仄句仄仄仄读平平仄仄韵",
            "仄仄平平仄句平平仄平句平仄仄平仄韵",
            "平平仄仄平平句仄平平仄平句平仄平仄韵",
            "平平仄仄句仄仄平平仄句平平平仄韵",
            "仄平平仄仄句仄仄仄读平平仄仄韵",
            "仄仄平平仄句平平仄平平仄仄韵"
        ],
        "origin": "日色西沈，上高台，迥观天地寥廓。疏星隐现，又一轮明月，昭昭无著。皓然三界外，似百炼、青铜镜濯。处处恩光被，家家照临，庭户起冥漠。长安万里清风，助乾坤荡摇，云雾难作。仙宫玉殿，正炼霞金碧，相辉参错。大哉清夜景，镇万古、含弘磊落。有志攀青桂，蟾宫兔边看捣药。",
        "origin_trad": "日色西沈，上高臺，迥觀天地寥廓。疏星隱現，又一輪明月，昭昭無著。晧然三界外，似百煉、青銅鏡濯。處處恩光被，家家照臨，庭戶起冥漠。長安萬里清風，助乾坤蕩搖，雲霧難作。仙宮玉殿，正煉霞金碧，相輝參錯。大哉清夜景，鎮萬古、含弘磊落。有志攀青桂，蟾宮兔邊看搗藥。"
    },
    {
        "ge_lyu_str": "平仄平平仄平平仄仄平仄平平平平仄仄仄平仄平平平仄平平仄平平仄仄仄平仄平平仄仄仄仄平仄平平平仄平平仄平仄平仄仄仄平平仄平平仄仄平平平仄仄仄仄平仄平仄平平平仄平平平平平仄仄仄平仄平平平仄仄平仄仄平平仄仄平平仄",
        "rhyme_pos": [
            3,
            12,
            25,
            37,
            42,
            50,
            56,
            65,
            78,
            90,
            101
        ],
        "yun_classify": {
            "0": [
                3,
                12,
                25,
                -37,
                42,
                -50,
                56,
                -65,
                78,
                -90,
                -101
            ]
        },
        "ci_sep": [
            "春满皇州",
            "见祥烟拥日　初照龙楼",
            "宫花苑柳　映仙仗云移　金鼎香浮",
            "宝光生玉斧　听鸣凤　箫韶乐奏",
            "德与和气游",
            "天生圣人　千载希有",
            "祥瑞电绕虹流",
            "有云成五色　芝生三秀",
            "四海太平　致民物雍熙　朝野歌讴",
            "千官齐拜舞　玉杯进　长生春酒",
            "愿皇庆万年　天子与天齐寿"
        ],
        "ge_lyu_sep": [
            "平仄平平韵",
            "仄平平仄仄句平仄平平韵",
            "平平仄仄句仄平仄平平句平仄平平韵",
            "仄平平仄仄句仄平仄读平平仄仄叶",
            "仄仄平仄平韵",
            "平平仄平句平仄平仄叶",
            "平仄仄仄平平韵",
            "仄平平仄仄句平平平仄叶",
            "仄仄仄平句仄平仄平平句平仄平平韵",
            "平平平仄仄句仄平仄读平平平仄叶",
            "仄平仄仄平句平仄仄平平仄叶"
        ],
        "origin": "春满皇州。见祥烟拥日，初照龙楼。宫花苑柳，映仙仗云移，金鼎香浮。宝光生玉斧，听鸣凤、箫韶乐奏。德与和气游。天生圣人，千载希有。祥瑞电绕虹流。有云成五色，芝生三秀。四海太平，致民物雍熙，朝野歌讴。千官齐拜舞，玉杯进、长生春酒。愿皇庆万年，天子与天齐寿。",
        "origin_trad": "春滿皇州。見祥煙擁日，初照龍樓。宮花苑柳，映仙仗雲移，金鼎香浮。寶光生玉斧，聽鳴鳳、簫韶樂奏。德與和氣游。天生聖人，千載希有。祥瑞電繞虹流。有雲成五色，芝生三秀。四海太平，致民物雍熙，朝野歌謳。千官齊拜舞，玉杯進、長生春酒。願皇慶萬年，天子與天齊壽。"
    }
]