[
    {
        "ge_lyu_str": "平仄平平平仄仄仄平平仄仄平平仄仄仄平平仄仄仄平平平仄平平平平仄仄仄仄平平仄仄仄仄仄平平仄仄仄仄平平平平仄仄平平平仄仄仄仄仄平平平仄仄仄平平仄仄仄平平平仄平平仄仄平平仄仄平平仄平平仄仄平平仄仄仄平平",
        "rhyme_pos": [
            13,
            23,
            35,
            48,
            62,
            73,
            85,
            97
        ],
        "yun_classify": {
            "0": [
                13,
                23,
                35,
                48,
                62,
                73,
                85,
                97
            ]
        },
        "ci_sep": [
            "今岁花时深院　尽日东风　荡飏茶烟",
            "但有绿苔芳草　柳絮榆钱",
            "闻道城西　长林古寺　甲第名园",
            "有国艳带酒　天香染袂　为我留连",
            "清明过了　残红无处　对此泪洒尊前",
            "秋向晚　一枝何事　向我依然",
            "高会聊追短景　清商不假馀妍",
            "不如留取　十分春态　付与明年"
        ],
        "ge_lyu_sep": [
            "平仄平平平仄句仄仄平平句仄仄平平韵",
            "仄仄仄平平仄句仄仄平平韵",
            "平仄平平句平平仄仄句仄仄平平韵",
            "仄仄仄仄仄句平平仄仄句仄仄平平韵",
            "平平仄仄句平平平仄句仄仄仄仄平平韵",
            "平仄仄读仄平平仄句仄仄平平韵",
            "平仄平平仄仄句平平仄仄平平韵",
            "仄平平仄句仄平平仄句仄仄平平韵"
        ],
        "origin": "今岁花时深院，尽日东风，荡飏茶烟。但有绿苔芳草，柳絮榆钱。闻道城西，长林古寺，甲第名园。有国艳带酒，天香染袂，为我留连。清明过了，残红无处，对此泪洒尊前。秋向晚、一枝何事，向我依然。高会聊追短景，清商不假馀妍。不如留取，十分春态，付与明年。",
        "origin_trad": "今歲花時深院，盡日東風，蕩颺茶煙。但有綠苔芳草，柳絮榆錢。聞道城西，長林古寺，甲第名園。有國豔帶酒，天香染袂，為我留連。清明過了，殘紅無處，對此淚灑尊前。秋向晚、一枝何事，向我依然。高會聊追短景，清商不假餘妍。不如留取，十分春態，付與明年。"
    },
    {
        "ge_lyu_str": "仄仄平平仄仄仄平平平仄仄平平仄仄平平仄仄仄仄平平平仄平平仄仄仄平仄仄平平仄平平仄仄仄仄平平平仄平平平平仄仄平仄平平仄平仄仄平平平仄仄平平平仄平仄平平仄仄平平平仄平平仄仄平平仄平平仄平平仄仄平仄平平",
        "rhyme_pos": [
            13,
            23,
            35,
            48,
            62,
            73,
            85,
            97
        ],
        "yun_classify": {
            "0": [
                13,
                23,
                35,
                48,
                62,
                73,
                85,
                97
            ]
        },
        "ci_sep": [
            "一叶凌波　十里御风　烟鬟雾鬓萧萧",
            "认得江皋玉佩　水馆冰绡",
            "秋净明霞乍吐　曙凉宿霭初消",
            "恨微颦不语　欲进还休　凝伫迢遥",
            "神交冉冉　愁思盈盈　断魂欲遣谁招",
            "还似待　青鸾传信　乌鹊成桥",
            "怅望胎仙琴叠　羞看翡翠兰苕",
            "梦回人远　红云一片　天际笙箫"
        ],
        "ge_lyu_sep": [
            "仄仄平平句仄仄仄平句平平仄仄平平韵",
            "仄仄平平仄仄句仄仄平平韵",
            "平仄平平仄仄句仄平仄仄平平韵",
            "仄平平仄仄句仄仄平平句平仄平平韵",
            "平平仄仄句平仄平平句仄平仄仄平平韵",
            "平仄仄读平平平仄句平仄平平韵",
            "仄仄平平平仄句平平仄仄平平韵",
            "仄平平仄句平平仄仄句平仄平平韵"
        ],
        "origin": "一叶凌波，十里御风，烟鬟雾鬓萧萧。认得江皋玉佩，水馆冰绡。秋净明霞乍吐，曙凉宿霭初消。恨微颦不语，欲进还休，凝伫迢遥。神交冉冉，愁思盈盈，断魂欲遣谁招。还似待、青鸾传信，乌鹊成桥。怅望胎仙琴叠，羞看翡翠兰苕。梦回人远，红云一片，天际笙箫。",
        "origin_trad": "一葉凌波，十里御風，煙鬟霧鬢蕭蕭。認得江皋玉佩，水館冰綃。秋淨明霞乍吐，曙凉宿靄初消。恨微顰不語，欲進還休，凝竚迢遙。神交冉冉，愁思盈盈，斷魂欲遣誰招。還似待、青鸞傳信，烏鵲成橋。悵望胎仙琴疊，羞看翡翠蘭苕。夢回人遠，紅雲一片，天際笙簫。"
    },
    {
        "ge_lyu_str": "仄仄平平仄仄仄平仄平平仄平平仄仄仄平平仄仄仄仄平平平仄平平仄仄仄平平仄平平仄平平仄仄仄仄平平仄仄平平平平平仄仄仄平平仄平仄仄平平仄平平仄平仄仄仄仄平平平仄仄平平仄仄平平仄平平仄平平仄平平平仄仄仄平平",
        "rhyme_pos": [
            13,
            24,
            36,
            49,
            63,
            74,
            86,
            98
        ],
        "yun_classify": {
            "0": [
                13,
                24,
                36,
                49,
                63,
                74,
                86,
                98
            ]
        },
        "ci_sep": [
            "缥蒂缃枝　玉叶翡英　百梢争趁春忙",
            "正雨后　蜂粘落絮　燕扑晴香",
            "遗策谁家荡子　唾花何处新妆",
            "想流红有恨　拾翠无心　往事凄凉",
            "春愁如海　客思翻空　带围只看东阳",
            "更那堪　玉笙度曲　翠羽传觞",
            "红泪不胜闺怨　白云应老他乡",
            "梦回敧枕　风惊庭树　月在西厢"
        ],
        "ge_lyu_sep": [
            "仄仄平平句仄仄仄平句仄平平仄平平韵",
            "仄仄仄读平平仄仄句仄仄平平韵",
            "平仄平平仄仄句仄平平仄平平韵",
            "仄平平仄仄句仄仄平平句仄仄平平韵",
            "平平平仄句仄仄平平句仄平仄仄平平韵",
            "仄平平读仄平仄仄句仄仄平平韵",
            "平仄仄平平仄句仄平平仄平平韵",
            "仄平平仄句平平平仄句仄仄平平韵"
        ],
        "origin": "缥蒂缃枝，玉叶翡英，百梢争趁春忙。正雨后、蜂粘落絮，燕扑晴香。遗策谁家荡子，唾花何处新妆。想流红有恨，拾翠无心，往事凄凉。春愁如海，客思翻空，带围只看东阳。更那堪、玉笙度曲，翠羽传觞。红泪不胜闺怨，白云应老他乡。梦回敧枕，风惊庭树，月在西厢。",
        "origin_trad": "縹蒂緗枝，玉葉翡英，百梢爭趁春忙。正雨後、蜂粘落絮，燕撲晴香。遺策誰家蕩子，唾花何處新妝。想流紅有恨，拾翠無心，往事淒凉。春愁如海，客思翻空，帶圍只看東陽。更那堪、玉笙度曲，翠羽傳觴。紅淚不勝閨怨，白雲應老他鄉。夢回敧枕，風驚庭樹，月在西厢。"
    },
    {
        "ge_lyu_str": "仄仄平平平平仄仄平仄仄仄平平仄平平平仄平仄平平仄仄仄平平仄仄仄平仄仄平平仄平平仄仄仄仄平平平仄平平平平仄仄仄仄仄平平仄仄平仄平平仄平仄平平平仄平平仄平仄平平仄仄平平平仄仄平平仄平平仄仄仄平平仄仄仄平平",
        "rhyme_pos": [
            13,
            22,
            35,
            48,
            63,
            72,
            86,
            99
        ],
        "yun_classify": {
            "0": [
                13,
                22,
                35,
                48,
                63,
                72,
                86,
                99
            ]
        },
        "ci_sep": [
            "坠髻慵梳　愁蛾懒画　心绪事事阑珊",
            "觉新来憔悴　金缕衣宽",
            "认得这　疏狂意下　向人诮　譬如閒",
            "把芳容整顿　恁地轻孤　争忍心安",
            "依前过了旧约　甚当初赚我　偷剪香鬟",
            "几时得归来　香阁深关",
            "待伊要　尤云殢雨　缠鸳衾　不与同欢",
            "尽更深款款　问伊今后　更敢无端"
        ],
        "ge_lyu_sep": [
            "仄仄平平句平平仄仄句平仄仄仄平平韵",
            "仄平平平仄句平仄平平韵",
            "仄仄仄读平平仄仄句仄平仄读仄平平韵",
            "仄平平仄仄句仄仄平平句平仄平平韵",
            "平平仄仄仄仄句仄平平仄仄句平仄平平韵",
            "仄平仄平平句平仄平平韵",
            "仄平仄读平平仄仄句平平平读仄仄平平韵",
            "仄平平仄仄句仄平平仄句仄仄平平韵"
        ],
        "origin": "坠髻慵梳，愁蛾懒画，心绪事事阑珊。觉新来憔悴，金缕衣宽。认得这、疏狂意下，向人诮、譬如閒。把芳容整顿，恁地轻孤，争忍心安。依前过了旧约，甚当初赚我，偷剪香鬟。几时得归来，香阁深关。待伊要、尤云殢雨，缠鸳衾、不与同欢。尽更深款款，问伊今后，更敢无端。",
        "origin_trad": "墜髻慵梳，愁蛾懶畫，心緒事事闌珊。覺新來憔悴，金縷衣寬。認得這、疏狂意下，向人誚、譬如閒。把芳容整頓，恁地輕孤，爭忍心安。依前過了舊約，甚當初賺我，偷翦香鬟。幾時得歸來，香閣深關。待伊要、尤雲殢雨，纏鴛衾、不與同歡。盡更深款款，問伊今後，更敢無端。"
    },
    {
        "ge_lyu_str": "仄中平中中中仄中中平中仄平平仄中平中仄中仄平平中仄中平中仄中平中仄平平仄平平中仄中中中中中仄平平中平中仄中中平中中中中仄平平中仄仄平平中仄中仄平平中仄中平中仄中平中仄平平中平中仄中平中仄中仄平平",
        "rhyme_pos": [
            13,
            22,
            34,
            47,
            61,
            72,
            84,
            96
        ],
        "yun_classify": {
            "0": [
                13,
                22,
                34,
                47,
                61,
                72,
                84,
                96
            ]
        },
        "ci_sep": [
            "眷浓恩重　长离永别　凭谁为返香魂",
            "忆湘裙霞袖　杏脸樱唇",
            "眉埽春山淡淡　眼裁秋水盈盈",
            "便如何忘得　温柔情态　恬静天真",
            "凭栏念及　夕阳西下　暮烟四起江村",
            "渐入夜　疏星映柳　新月笼云",
            "酝造一生清瘦　能消几个黄昏",
            "断肠时候　帘垂深院　人掩重门"
        ],
        "ge_lyu_sep": [
            "仄中平中句中中仄中句中平中仄平平韵",
            "仄中平中仄句中仄平平韵",
            "中仄中平中仄句中平中仄平平韵",
            "仄平平中仄句中中中中句中仄平平韵",
            "中平中仄句中中平中句中中中仄平平韵",
            "中仄仄读平平中仄句中仄平平韵",
            "中仄中平中仄句中平中仄平平韵",
            "中平中仄句中平中仄句中仄平平韵"
        ],
        "origin": "眷浓恩重，长离永别，凭谁为返香魂。忆湘裙霞袖，杏脸樱唇。眉埽春山淡淡，眼裁秋水盈盈。便如何忘得，温柔情态，恬静天真。凭栏念及，夕阳西下，暮烟四起江村。渐入夜、疏星映柳，新月笼云。酝造一生清瘦，能消几个黄昏。断肠时候，帘垂深院，人掩重门。",
        "origin_trad": "眷濃恩重，長離永別，憑誰為返香魂。憶湘裙霞袖，杏臉櫻脣。眉埽春山淡淡，眼裁秋水盈盈。便如何忘得，溫柔情態，恬靜天真。憑欄念及，夕陽西下，暮煙四起江邨。漸入夜、疏星映柳，新月籠雲。醞造一生清瘦，能消幾箇黃昏。斷腸時候，簾垂深院，人掩重門。"
    },
    {
        "ge_lyu_str": "仄仄平平平平仄仄仄平仄仄平平仄仄平仄仄平仄平平仄仄平平仄仄平平平仄平平平平仄仄仄平仄仄仄仄平平仄平平仄平仄平平平平仄仄平平平仄仄平平仄仄仄仄平平仄仄仄平仄仄平平仄仄平平平平仄仄平平平仄仄仄平平",
        "rhyme_pos": [
            13,
            22,
            34,
            46,
            60,
            71,
            83,
            95
        ],
        "yun_classify": {
            "0": [
                13,
                22,
                34,
                46,
                60,
                71,
                83,
                95
            ]
        },
        "ci_sep": [
            "玉局祠前　铜壶阁畔　锦城药市争奇",
            "正紫萸缀席　黄菊浮卮",
            "巷陌联镳并辔　楼台吹竹弹丝",
            "登高望远　一年好景　九日佳期",
            "自怜行客　犹对嘉宾　留连岂是贪痴",
            "谁会得　心驰北阙　兴寄东篱",
            "惜别未催鹢首　追欢且醉蛾眉",
            "明年此会　他乡今日　总是相思"
        ],
        "ge_lyu_sep": [
            "仄仄平平句平平仄仄句仄平仄仄平平韵",
            "仄仄平仄仄句平仄平平韵",
            "仄仄平平仄仄句平平平仄平平韵",
            "平平仄仄句仄平仄仄句仄仄平平韵",
            "仄平平仄句平仄平平句平平仄仄平平韵",
            "平仄仄读平平仄仄句仄仄平平韵",
            "仄仄仄平仄仄句平平仄仄平平韵",
            "平平仄仄句平平平仄句仄仄平平韵"
        ],
        "origin": "玉局祠前，铜壶阁畔，锦城药市争奇。正紫萸缀席，黄菊浮卮。巷陌联镳并辔，楼台吹竹弹丝。登高望远，一年好景，九日佳期。自怜行客，犹对嘉宾，留连岂是贪痴。谁会得、心驰北阙，兴寄东篱。惜别未催鹢首，追欢且醉蛾眉。明年此会，他乡今日，总是相思。",
        "origin_trad": "玉局祠前，銅壺閣畔，錦城藥市爭奇。正紫萸綴席，黃菊浮卮。巷陌聯鑣並轡，樓臺吹竹彈絲。登高望遠，一年好景，九日佳期。自憐行客，猶對嘉賓，留連豈是貪癡。誰會得、心馳北闕，興寄東籬。惜別未催鷁首，追歡且醉蛾眉。明年此會，他鄉今日，總是相思。"
    },
    {
        "ge_lyu_str": "仄仄平平仄仄平仄平平仄仄平平仄仄平平平平仄仄平平平仄平平平仄仄平仄仄平平仄平平平仄仄仄平平仄仄平平平平仄仄仄仄平平平仄仄仄平平平仄仄平平仄仄仄仄平平平仄平平平仄仄平仄仄平平仄平仄仄平平平仄仄仄平平",
        "rhyme_pos": [
            13,
            23,
            35,
            48,
            62,
            73,
            85,
            97
        ],
        "yun_classify": {
            "0": [
                13,
                23,
                35,
                48,
                62,
                73,
                85,
                97
            ]
        },
        "ci_sep": [
            "旆拂西风　客应星汉　行参玉节征鞍",
            "缓带轻裘　争看盛世衣冠",
            "吟倦西湖风月　去看北塞关山",
            "过离宫禾黍　故垒烟尘　有泪应弹",
            "文章俊伟　颖露囊锋　名动万里呼韩",
            "知素有　平戎手段　小试何难",
            "情寄吴梅香冷　梦随陇雁霜寒",
            "立勋未晚　归来依旧　酒社诗坛"
        ],
        "ge_lyu_sep": [
            "仄仄平平句仄仄平仄句平平仄仄平平韵",
            "仄仄平平句平平仄仄平平韵",
            "平仄平平平仄句仄平仄仄平平韵",
            "仄平平平仄句仄仄平平句仄仄平平韵",
            "平平仄仄句仄仄平平句平仄仄仄平平韵",
            "平仄仄读平平仄仄句仄仄平平韵",
            "平仄平平平仄句仄平仄仄平平韵",
            "仄平仄仄句平平平仄句仄仄平平韵"
        ],
        "origin": "旆拂西风，客应星汉，行参玉节征鞍。缓带轻裘，争看盛世衣冠。吟倦西湖风月，去看北塞关山。过离宫禾黍，故垒烟尘，有泪应弹。文章俊伟，颖露囊锋，名动万里呼韩。知素有、平戎手段，小试何难。情寄吴梅香冷，梦随陇雁霜寒。立勋未晚，归来依旧，酒社诗坛。",
        "origin_trad": "旆拂西風，客應星漢，行參玉節征鞍。緩帶輕裘，爭看盛世衣冠。吟倦西湖風月，去看北塞關山。過離宮禾黍，故壘煙塵，有淚應彈。文章俊偉，穎露囊鋒，名動萬里呼韓。知素有、平戎手段，小試何難。情寄吳梅香冷，夢隨隴雁霜寒。立勛未晚，歸來依舊，酒社詩壇。"
    },
    {
        "ge_lyu_str": "仄仄平平仄仄仄平平平平仄平平仄仄仄平平仄仄平平平仄平平仄仄仄平平仄平平仄平平平仄仄仄平平平仄平平仄平仄仄平仄平平仄平平仄平平平仄仄平平平仄仄仄平平仄仄平平仄仄平平平仄平平仄平平仄仄平平仄仄仄平平",
        "rhyme_pos": [
            13,
            22,
            34,
            47,
            61,
            72,
            84,
            96
        ],
        "yun_classify": {
            "0": [
                13,
                22,
                34,
                47,
                61,
                72,
                84,
                96
            ]
        },
        "ci_sep": [
            "寄径睢阳　陌上忽看　夭桃秾李争春",
            "又见楚宫　行雨洗芳尘",
            "红艳霞光夕照　素华琼树朝新",
            "为奇姿芳润　拟倩游丝　留住东君",
            "拾遗杜老　犹爱南塘　寄情萝薜山村",
            "争似此　花如姝丽　獭髓轻匀",
            "不数江陵玉杖　休誇花岛红云",
            "少须澄霁　一番清影　更待冰轮"
        ],
        "ge_lyu_sep": [
            "仄仄平平句仄仄仄平句平平平仄平平韵",
            "仄仄仄平句平仄仄平平韵",
            "平仄平平仄仄句仄平平仄平平韵",
            "仄平平平仄句仄仄平平句平仄平平韵",
            "仄平仄仄句平仄平平句仄平平仄平平韵",
            "平仄仄读平平平仄句仄仄平平韵",
            "仄仄平平仄仄句平平平仄平平韵",
            "仄平平仄句仄平平仄句仄仄平平韵"
        ],
        "origin": "寄径睢阳，陌上忽看，夭桃秾李争春。又见楚宫，行雨洗芳尘。红艳霞光夕照，素华琼树朝新。为奇姿芳润，拟倩游丝，留住东君。拾遗杜老，犹爱南塘，寄情萝薜山村。争似此、花如姝丽，獭髓轻匀。不数江陵玉杖，休誇花岛红云。少须澄霁，一番清影，更待冰轮。",
        "origin_trad": "寄徑睢陽，陌上忽看，夭桃穠李爭春。又見楚宮，行雨洗芳塵。紅豔霞光夕照，素華瓊樹朝新。為奇姿芳潤，擬倩游絲，留住東君。拾遺杜老，猶愛南塘，寄情蘿薜山邨。爭似此、花如姝麗，獺髓輕勻。不數江陵玉杖，休誇花島紅雲。少須澄霽，一番清影，更待冰輪。"
    },
    {
        "ge_lyu_str": "仄仄平平平仄仄仄平平仄仄平平仄仄平平仄仄仄平平平仄仄平平仄平平仄仄平平平平仄仄平平平仄仄仄平平平平仄仄仄平平仄仄仄仄仄平平平仄仄平平平仄平仄平平仄仄仄平平仄仄平平仄平平仄平平仄仄平平仄仄仄平平",
        "rhyme_pos": [
            13,
            22,
            34,
            46,
            60,
            71,
            83,
            95
        ],
        "yun_classify": {
            "0": [
                13,
                22,
                34,
                46,
                60,
                71,
                83,
                95
            ]
        },
        "ci_sep": [
            "事往人离　还似暮峡归云　陇上流泉",
            "奈向分圆镜　已断幺弦",
            "长记酒阑歌罢　难忘月夕花前",
            "相携手处　琼楼朱户　触目依然",
            "从来惯共　绣帏罗帐　镇效比翼文鸳",
            "谁念我　而今清夜　常是孤眠",
            "入户不如飞絮　傍怀争及炉烟",
            "这回休也　一生心事　为你萦牵"
        ],
        "ge_lyu_sep": [
            "仄仄平平句平仄仄仄平平句仄仄平平韵",
            "仄仄平平仄句仄仄平平韵",
            "平仄仄平平仄句平平仄仄平平韵",
            "平平仄仄句平平平仄句仄仄平平韵",
            "平平仄仄句仄平平仄句仄仄仄仄平平韵",
            "平仄仄读平平平仄句平仄平平韵",
            "仄仄仄平平仄句仄平平仄平平韵",
            "仄平平仄句仄平平仄句仄仄平平韵"
        ],
        "origin": "事往人离，还似暮峡归云，陇上流泉。奈向分圆镜，已断幺弦。长记酒阑歌罢，难忘月夕花前。相携手处，琼楼朱户，触目依然。从来惯共，绣帏罗帐，镇效比翼文鸳。谁念我、而今清夜，常是孤眠。入户不如飞絮，傍怀争及炉烟。这回休也，一生心事，为你萦牵。",
        "origin_trad": "事往人離，還似暮峽歸雲，隴上流泉。奈向分圓鏡，已斷幺絃。長記酒闌歌罷，難忘月夕花前。相攜手處，瓊樓朱戶，觸目依然。從來慣共，繡幃羅帳，鎮效比翼文鴛。誰念我、而今清夜，常是孤眠。入戶不如飛絮，傍懷爭及爐煙。這回休也，一生心事，為你縈牽。"
    },
    {
        "ge_lyu_str": "仄仄中平平仄仄中平平仄中平仄仄平平平仄仄中平仄仄仄平平平仄平仄仄平平仄仄仄平平仄中中平中仄中平仄平平中仄中中中中中仄仄平平仄平中仄平平中仄仄平平仄仄仄中平中仄中平中仄平仄仄平平仄仄中平平仄仄中平仄",
        "rhyme_pos": [
            13,
            22,
            34,
            47,
            61,
            72,
            84,
            97
        ],
        "yun_classify": {
            "0": [
                13,
                22,
                34,
                47,
                61,
                72,
                84,
                97
            ]
        },
        "ci_sep": [
            "指点虚无征路　醉乘斑虬　远访西极",
            "见天风吹落　满空寒白",
            "玉女明星迎笑　何苦自淹尘域",
            "正火轮飞上　雾捲烟开　洞观金碧",
            "重重观阁　横枕鳌峰　水面倒衔苍石",
            "随处有　奇香异火　杳然难测",
            "好是蟠桃熟后　阿环偷报消息",
            "在青天碧海　一枝难遇　占取春色"
        ],
        "ge_lyu_sep": [
            "仄仄中平平仄句仄中平平句仄中平仄韵",
            "仄平平平仄句仄中平仄韵",
            "仄仄平平平仄句平仄仄平平仄韵",
            "仄仄平平仄句中中平中句仄中平仄韵",
            "平平中仄句中中中中句中仄仄平平仄韵",
            "平中仄读平平中仄句仄平平仄韵",
            "仄仄中平中仄句中平中仄平仄韵",
            "仄平平仄仄句中平平仄句仄中平仄韵"
        ],
        "origin": "指点虚无征路，醉乘斑虬，远访西极。见天风吹落，满空寒白。玉女明星迎笑，何苦自淹尘域。正火轮飞上，雾捲烟开，洞观金碧。重重观阁，横枕鳌峰，水面倒衔苍石。随处有、奇香异火，杳然难测。好是蟠桃熟后，阿环偷报消息。在青天碧海，一枝难遇，占取春色。",
        "origin_trad": "指點虛無征路，醉乘斑虯，遠訪西極。見天風吹落，滿空寒白。玉女明星迎笑，何苦自淹塵域。正火輪飛上，霧捲煙開，洞觀金碧。重重觀閣，橫枕鼇峰，水面倒銜蒼石。隨處有、奇香異火，杳然難測。好是蟠桃熟後，阿環偷報消息。在青天碧海，一枝難遇，占取春色。"
    },
    {
        "ge_lyu_str": "仄仄平平平仄仄仄平平仄平平仄仄仄平平平仄仄平平仄平仄平平平平仄仄仄平平仄仄仄平平仄平平平仄仄平平仄平平平仄仄仄仄平仄仄仄平平仄平仄仄平平仄仄仄平平仄仄仄仄平平仄平平平仄平仄仄平仄仄平平平仄仄平平仄",
        "rhyme_pos": [
            13,
            23,
            35,
            48,
            62,
            73,
            85,
            97
        ],
        "yun_classify": {
            "0": [
                13,
                23,
                35,
                48,
                62,
                73,
                85,
                97
            ]
        },
        "ci_sep": [
            "梦破江南春信　渐入江梅　暗香初发",
            "乞与横斜疏影　为怜清绝",
            "梁苑相如　平生有赋　未甘华发",
            "便广寒争遣　韶华惊怨　讵妨轻折",
            "扬州歌吹　二十四桥　不道画楼声歇",
            "生怕有　江边一树　要堆轻雪",
            "老去苦无欢事　凌波空有纤袜",
            "恨无好语　何郎风味　定教难说"
        ],
        "ge_lyu_sep": [
            "仄仄平平平仄句仄仄平平句仄平平仄韵",
            "仄仄平平平仄句仄平平仄韵",
            "平仄平平句平平仄仄句仄平平仄韵",
            "仄仄平平仄句平平平仄句仄平平仄韵",
            "平平平仄句仄仄仄平句仄仄仄平平仄韵",
            "平仄仄读平平仄仄句仄平平仄韵",
            "仄仄仄平平仄句平平平仄平仄韵",
            "仄平仄仄句平平平仄句仄平平仄韵"
        ],
        "origin": "梦破江南春信，渐入江梅，暗香初发。乞与横斜疏影，为怜清绝。梁苑相如，平生有赋，未甘华发。便广寒争遣，韶华惊怨，讵妨轻折。扬州歌吹，二十四桥，不道画楼声歇。生怕有、江边一树，要堆轻雪。老去苦无欢事，凌波空有纤袜。恨无好语，何郎风味，定教难说。",
        "origin_trad": "夢破江南春信，漸入江梅，暗香初發。乞與橫斜疏影，為憐清絕。梁苑相如，平生有賦，未甘華髮。便廣寒爭遣，韶華驚怨，詎妨輕折。揚州歌吹，二十四橋，不道畫樓聲歇。生怕有、江邊一樹，要堆輕雪。老去苦無歡事，凌波空有纖襪。恨無好語，何郎風味，定教難說。"
    },
    {
        "ge_lyu_str": "仄仄平平平仄仄仄平平仄平平仄仄平平平仄仄仄平仄平仄平平平平仄仄仄平平仄仄仄平平仄平平平仄仄仄平仄平平仄仄仄平平仄平仄仄平平仄平平仄平平平仄仄平平仄仄仄仄平仄仄平平仄仄平仄仄平仄仄仄平平仄仄平平仄",
        "rhyme_pos": [
            13,
            22,
            34,
            47,
            61,
            72,
            84,
            96
        ],
        "yun_classify": {
            "0": [
                13,
                22,
                34,
                47,
                61,
                72,
                84,
                96
            ]
        },
        "ci_sep": [
            "正乐中和　夷夏燕喜　官梅乍传消息",
            "待新年欢计　断送春色",
            "桃李成阴　甘棠少讼　又移旌戟",
            "念画楼朱阁　风流高会　顿冷谈席",
            "西川纵有　舞裙歌板　谁共茗邀棋敌",
            "归来未　先沾离袖　管弦催滴",
            "乐事赏心易散　良辰美景难得",
            "会须醉倒　玉山扶起　更倾春碧"
        ],
        "ge_lyu_sep": [
            "仄仄平平句平仄仄仄句平平仄平平仄韵",
            "仄平平平仄句仄仄平仄韵",
            "平仄平平句平平仄仄句仄平平仄韵",
            "仄仄平平仄句平平平仄句仄仄平仄韵",
            "平平仄仄句仄平平仄句平仄仄平平仄韵",
            "平平仄读平平平仄句仄平平仄韵",
            "仄仄仄平仄仄句平平仄仄平仄韵",
            "仄平仄仄句仄平平仄句仄平平仄韵"
        ],
        "origin": "正乐中和，夷夏燕喜，官梅乍传消息。待新年欢计，断送春色。桃李成阴，甘棠少讼，又移旌戟。念画楼朱阁，风流高会，顿冷谈席。西川纵有，舞裙歌板，谁共茗邀棋敌。归来未、先沾离袖，管弦催滴。乐事赏心易散，良辰美景难得。会须醉倒，玉山扶起，更倾春碧。",
        "origin_trad": "正樂中和，夷夏燕喜，官梅乍傳消息。待新年歡計，斷送春色。桃李成陰，甘棠少訟，又移旌戟。念畫樓朱閣，風流高會，頓冷談席。西川縱有，舞裙歌板，誰共茗邀棋敵。歸來未、先霑離袖，管絃催滴。樂事賞心易散，良辰美景難得。會須醉倒，玉山扶起，更傾春碧。"
    },
    {
        "ge_lyu_str": "仄仄仄平平仄仄仄平平仄平平仄仄仄平平平仄仄仄平仄仄仄平平平平仄仄仄平平仄仄仄平平仄平平平仄仄平平仄平平仄仄平平仄仄仄仄平平仄平仄仄平平平仄仄平平仄仄仄平平仄仄平平仄仄平仄仄平仄仄平平平仄仄平平仄",
        "rhyme_pos": [
            13,
            23,
            35,
            40,
            48,
            61,
            72,
            84,
            88,
            96
        ],
        "yun_classify": {
            "0": [
                13,
                23,
                35,
                40,
                48,
                61,
                72,
                84,
                88,
                96
            ]
        },
        "ci_sep": [
            "宴阕倚阑郊外　乍别芳姿　醉登长陌",
            "渐觉联绵离绪　淡薄秋色",
            "宝马频嘶　寒蝉噪晚　正伤行客",
            "念少年踪迹",
            "风流声价　泪珠偷滴",
            "从前与　酒朋花侣　镇赏画楼瑶席",
            "今夜里　清风明月　水村山驿",
            "往事悠悠似梦　新愁苒苒如织",
            "断肠望极",
            "重逢何处　暮云凝碧"
        ],
        "ge_lyu_sep": [
            "仄仄仄平平仄句仄仄平平句仄平平仄韵",
            "仄仄平平平仄句仄仄平仄韵",
            "仄仄平平句平平仄仄句仄平平仄韵",
            "仄仄平平仄韵",
            "平平平仄句仄平平仄韵",
            "平平仄读仄平平仄句仄仄仄平平仄韵",
            "平仄仄读平平平仄句仄平平仄韵",
            "仄仄平平仄仄句平平仄仄平仄韵",
            "仄平仄仄韵",
            "平平平仄句仄平平仄韵"
        ],
        "origin": "宴阕倚阑郊外，乍别芳姿，醉登长陌。渐觉联绵离绪，淡薄秋色。宝马频嘶，寒蝉噪晚，正伤行客。念少年踪迹。风流声价，泪珠偷滴。从前与、酒朋花侣，镇赏画楼瑶席。今夜里、清风明月，水村山驿。往事悠悠似梦，新愁苒苒如织。断肠望极。重逢何处，暮云凝碧。",
        "origin_trad": "宴闋倚闌郊外，乍別芳姿，醉登長陌。漸覺聯綿離緒，淡薄秋色。寶馬頻嘶，寒蟬噪晚，正傷行客。念少年蹤跡。風流聲價，淚珠偷滴。從前與、酒朋花侶，鎮賞畫樓瑤席。今夜裏、清風明月，水邨山驛。往事悠悠似夢，新愁苒苒如織。斷腸望極。重逢何處，暮雲凝碧。"
    }
]