[
    {
        "ge_lyu_str": "中平仄仄中中中仄中中仄平平仄仄平平中中中中平仄平平中仄中中仄中中中中仄仄平平仄仄平平仄中平中平仄平中仄仄平仄平平仄平平仄中平仄仄仄平平平平仄仄中仄中平中仄平平中平平中仄仄中仄中中中中仄仄平平仄仄平平仄中中中平仄",
        "rhyme_pos": [
            2,
            10,
            22,
            26,
            34,
            47,
            53,
            62,
            76,
            83,
            91,
            104
        ],
        "yun_classify": {
            "0": [
                2,
                10,
                22,
                26,
                34,
                47,
                53,
                62,
                76,
                83,
                91,
                104
            ]
        },
        "ci_sep": [
            "宠嘉丽",
            "算九衢红粉皆难比",
            "天然嫩脸修蛾　不假施朱描翠",
            "盈盈秋水",
            "恣雅态　欲语先娇媚",
            "每相逄　月夕花朝　自有怜才深意",
            "绸缪凤枕鸳被",
            "深深处　琼枝玉树相倚",
            "困极欢馀　芙蓉帐暖　别是恼人情味",
            "风流事　难逢双美",
            "况已断　香云为盟誓",
            "且相将　尽意平生　未肯轻分连理"
        ],
        "ge_lyu_sep": [
            "中平仄韵",
            "仄中中中仄中中仄韵",
            "平平仄仄平平句中中中中平仄韵",
            "平平中仄韵",
            "中中仄读中中中中仄韵",
            "仄平平读仄仄平平句仄中平中平仄韵",
            "平中仄仄平仄韵",
            "平平仄读平平仄中平仄韵",
            "仄仄平平句平平仄仄句中仄中平中仄韵",
            "平平中读平平中仄韵",
            "仄中仄读中中中中仄韵",
            "仄平平读仄仄平平句仄中中中平仄韵"
        ],
        "origin": "宠嘉丽。算九衢红粉皆难比。天然嫩脸修蛾，不假施朱描翠。盈盈秋水。恣雅态、欲语先娇媚。每相逄、月夕花朝，自有怜才深意。绸缪凤枕鸳被。深深处、琼枝玉树相倚。困极欢馀，芙蓉帐暖，别是恼人情味。风流事、难逢双美。况已断、香云为盟誓。且相将、尽意平生，未肯轻分连理。",
        "origin_trad": "寵嘉麗。算九衢紅粉皆難比。天然嫩臉修蛾，不假施朱描翠。盈盈秋水。恣雅態、欲語先嬌媚。每相逄、月夕花朝，自有憐才深意。綢繆鳳枕鴛被。深深處、瓊枝玉樹相倚。困極歡餘，芙蓉帳暖，別是惱人情味。風流事、難逢雙美。况已斷、香雲為盟誓。且相將、盡意平生，未肯輕分連理。"
    },
    {
        "ge_lyu_str": "仄平仄仄平平仄仄平仄仄平平仄仄平平平平仄平平仄平平平仄平平仄仄仄平平仄仄平平仄仄平平仄平平仄平仄平平仄仄平平平平仄平平仄仄平仄仄仄平平平平仄仄平仄仄平平仄平平仄平平平仄仄平仄平平平平仄仄平平仄仄平平仄平平平平仄",
        "rhyme_pos": [
            2,
            10,
            22,
            26,
            34,
            47,
            62,
            76,
            83,
            91,
            104
        ],
        "yun_classify": {
            "0": [
                2,
                10,
                22,
                26,
                34,
                47,
                62,
                76,
                83,
                91,
                104
            ]
        },
        "ci_sep": [
            "岁云暮",
            "叹光阴苒苒能几许",
            "江梅尚怯馀寒　长安信音犹阻",
            "春风无据",
            "凭阑久　欲去还凝伫",
            "忆溪边　月夜徘徊　暗香疏影庭户",
            "朝来冻解霜消　南枝上　香英数点微露",
            "把酒看花　无言有泪　还是那时情绪",
            "花依旧　晨妆何处",
            "漫赢得　花前愁千缕",
            "尽高楼　画角频吹　任教纷纷飞素"
        ],
        "ge_lyu_sep": [
            "仄平仄韵",
            "仄平平仄仄平仄仄韵",
            "平平仄仄平平句平平仄平平仄韵",
            "平平平仄韵",
            "平平仄读仄仄平平仄韵",
            "仄平平读仄仄平平句仄平平仄平仄韵",
            "平平仄仄平平句平平仄读平平仄仄平仄韵",
            "仄仄平平句平平仄仄句平仄仄平平仄韵",
            "平平仄读平平平仄韵",
            "仄平仄读平平平平仄韵",
            "仄平平读仄仄平平句仄平平平平仄韵"
        ],
        "origin": "岁云暮。叹光阴苒苒能几许。江梅尚怯馀寒，长安信音犹阻。春风无据。凭阑久、欲去还凝伫。忆溪边、月夜徘徊，暗香疏影庭户。朝来冻解霜消，南枝上、香英数点微露。把酒看花，无言有泪，还是那时情绪。花依旧、晨妆何处。漫赢得、花前愁千缕。尽高楼、画角频吹，任教纷纷飞素。",
        "origin_trad": "歲雲暮。歎光陰苒苒能幾許。江梅尚怯餘寒，長安信音猶阻。春風無據。憑闌久、欲去還凝竚。憶溪邊、月夜徘徊，暗香疏影庭戶。朝來凍解霜消，南枝上、香英數點微露。把酒看花，無言有淚，還是那時情緒。花依舊、晨妝何處。漫贏得、花前愁千縷。儘高樓、畫角頻吹，任教紛紛飛素。"
    },
    {
        "ge_lyu_str": "仄平仄仄平平仄仄平平仄平平仄仄平平平仄仄平平仄平平平仄仄平仄平仄平平仄仄平平仄仄平平仄仄平平平仄仄平仄平平仄平平仄平平仄平平仄仄仄平平平平仄仄平仄仄平平仄平平仄平平平仄仄平仄平仄平平仄仄平平仄仄平平仄仄平平平仄",
        "rhyme_pos": [
            2,
            10,
            22,
            26,
            34,
            47,
            50,
            53,
            62,
            70,
            76,
            83,
            91,
            104
        ],
        "yun_classify": {
            "0": [
                2,
                10,
                22,
                26,
                34,
                47,
                50,
                53,
                62,
                70,
                76,
                83,
                91,
                104
            ]
        },
        "ci_sep": [
            "胜游地",
            "信东吴绝景饶佳丽",
            "平湖底　见层岚　凉月下　闻清吹",
            "人如秾李",
            "泛衿袂　香润蘋风起",
            "喜凌波　素袜逢迎　领略当歌深意",
            "鄂君被",
            "双鸳绮",
            "垂杨荫　夷犹画舲相舣",
            "宝瑟弦调　明珠佩委",
            "回首碧云千里",
            "归鸿后　芳音谁寄",
            "念怀系　青鬓今无几",
            "枉分将　镜里华年　付与楼前流水"
        ],
        "ge_lyu_sep": [
            "仄平仄韵",
            "仄平平仄仄平平仄韵",
            "平平仄句仄平平句平仄仄句平平仄韵",
            "平平平仄韵",
            "仄平仄读平仄平平仄韵",
            "仄平平读仄仄平平句仄仄平平平仄韵",
            "仄平仄韵",
            "平平仄韵",
            "平平仄读平平仄平平仄韵",
            "仄仄平平句平平仄仄韵",
            "平仄仄平平仄韵",
            "平平仄读平平平仄韵",
            "仄平仄读平仄平平仄韵",
            "仄平平读仄仄平平句仄仄平平平仄韵"
        ],
        "origin": "胜游地。信东吴绝景饶佳丽。平湖底，见层岚，凉月下，闻清吹。人如秾李。泛衿袂、香润蘋风起。喜凌波、素袜逢迎，领略当歌深意。鄂君被。双鸳绮。垂杨荫、夷犹画舲相舣。宝瑟弦调，明珠佩委。回首碧云千里。归鸿后、芳音谁寄。念怀系、青鬓今无几。枉分将、镜里华年，付与楼前流水。",
        "origin_trad": "勝游地。信東吳絕景饒佳麗。平湖底，見層嵐，凉月下，聞清吹。人如穠李。泛衿袂、香潤蘋風起。喜凌波、素襪逢迎，領略當歌深意。鄂君被。雙鴛綺。垂楊蔭、夷猶畫舲相檥。寶瑟絃調，明珠佩委。回首碧雲千里。歸鴻後、芳音誰寄。念懷繫、青鬢今無幾。枉分將、鏡裏華年，付與樓前流水。"
    },
    {
        "ge_lyu_str": "平平仄仄仄仄仄仄平平仄平平仄仄平平平仄平平平仄平平仄仄平仄仄平平仄平仄仄平平仄仄平平仄平平仄平仄平平仄仄平平平平仄平平仄仄平仄仄仄平平平平仄平仄仄平平仄仄平平仄平平仄仄仄平仄平平仄仄仄仄平平仄仄平平仄平平仄平仄",
        "rhyme_pos": [
            2,
            10,
            22,
            34,
            47,
            62,
            76,
            91,
            104
        ],
        "yun_classify": {
            "0": [
                2,
                10,
                22,
                34,
                47,
                62,
                76,
                91,
                104
            ]
        },
        "ci_sep": [
            "隋堤路",
            "渐日晚　密霭生深树",
            "阴阴淡月笼沙　还宿河桥深处",
            "无情画舸　都不管　烟波隔前浦",
            "等行人　醉拥重衾　载将离恨归去",
            "因思旧客京华　长偎傍　疏林小槛欢聚",
            "冶叶倡条俱相识　仍惯见　珠歌翠舞",
            "如今向　渔村水驿　夜如岁　焚香独自语",
            "有何人　念我无聊　梦魂凝想鸳侣"
        ],
        "ge_lyu_sep": [
            "平平仄韵",
            "仄仄仄读仄仄平平仄韵",
            "平平仄仄平平句平仄平平平仄韵",
            "平平仄仄句平仄仄读平平仄平仄韵",
            "仄平平读仄仄平平句仄平平仄平仄韵",
            "平平仄仄平平句平平仄读平平仄仄平仄韵",
            "仄仄平平平平仄句平仄仄读平平仄仄韵",
            "平平仄读平平仄仄句仄平仄读平平仄仄仄韵",
            "仄平平读仄仄平平句仄平平仄平仄韵"
        ],
        "origin": "隋堤路。渐日晚、密霭生深树。阴阴淡月笼沙，还宿河桥深处。无情画舸，都不管、烟波隔前浦。等行人、醉拥重衾，载将离恨归去。因思旧客京华，长偎傍、疏林小槛欢聚。冶叶倡条俱相识，仍惯见、珠歌翠舞。如今向、渔村水驿，夜如岁、焚香独自语。有何人、念我无聊，梦魂凝想鸳侣。",
        "origin_trad": "隋堤路。漸日晚、密靄生深樹。陰陰淡月籠沙，還宿河橋深處。無情畫舸，都不管、煙波隔前浦。等行人、醉擁重衾，載將離恨歸去。因思舊客京華，長偎傍、疏林小檻歡聚。冶葉倡條俱相識，仍慣見、珠歌翠舞。如今向、漁邨水驛，夜如歲、焚香獨自語。有何人、念我無聊，夢魂凝想鴛侶。"
    },
    {
        "ge_lyu_str": "仄平仄仄仄仄平仄仄仄仄平平仄仄平平平仄仄仄平仄仄仄仄平仄仄平仄平仄平仄仄平平平仄仄平仄仄仄平平平仄平平仄仄平仄仄平仄平平仄平仄仄仄仄平平平平仄仄仄仄仄平平仄平平仄平仄平仄仄平仄仄仄平平仄仄平平仄仄平平仄平仄仄平仄",
        "rhyme_pos": [
            2,
            10,
            22,
            27,
            35,
            48,
            54,
            63,
            77,
            84,
            92,
            105
        ],
        "yun_classify": {
            "0": [
                2,
                10,
                22,
                27,
                35,
                48,
                54,
                63,
                77,
                84,
                92,
                105
            ]
        },
        "ci_sep": [
            "碎云薄",
            "向碧玉枝上　缀万萼",
            "如将汞粉匀开　疑使柏麝熏却",
            "雪魄未应若",
            "况天赋　标艳仍绰约",
            "当暄风皎日佳处　戏蝶游蜂粘著",
            "重重绣帟珠箔",
            "障浓艳霏霏　异香漠漠",
            "见说徐妃　当年嫁了　信任玉钿零落",
            "无言自啼露萧索",
            "夜深待　月上阑干角",
            "广寒宫　要与姮娥　素妆一夜相觉"
        ],
        "ge_lyu_sep": [
            "仄平仄韵",
            "仄仄仄平仄读仄仄仄韵",
            "平平仄仄平平句平仄仄仄平仄韵",
            "仄仄仄平仄韵",
            "仄平仄读平仄平仄仄韵",
            "平平平仄仄平仄句仄仄平平平仄韵",
            "平平仄仄平仄韵",
            "仄平仄平平句仄平仄仄韵",
            "仄仄平平句平平仄仄句仄仄仄平平仄韵",
            "平平仄平仄平仄韵",
            "仄平仄读仄仄平平仄韵",
            "仄平平读仄仄平平句仄平仄仄平仄韵"
        ],
        "origin": "碎云薄。向碧玉枝上、缀万萼。如将汞粉匀开，疑使柏麝熏却。雪魄未应若。况天赋、标艳仍绰约。当暄风皎日佳处，戏蝶游蜂粘著。重重绣帟珠箔。障浓艳霏霏，异香漠漠。见说徐妃，当年嫁了，信任玉钿零落。无言自啼露萧索。夜深待、月上阑干角。广寒宫、要与姮娥，素妆一夜相觉。",
        "origin_trad": "碎雲薄。向碧玉枝上、綴萬萼。如將汞粉勻開，疑使柏麝熏却。雪魄未應若。况天賦、標豔仍綽約。當暄風皎日佳處，戲蝶遊蜂粘著。重重繡帟珠箔。障濃豔霏霏，異香漠漠。見說徐妃，當年嫁了，信任玉鈿零落。無言自啼露蕭索。夜深待、月上闌干角。廣寒宮、要與姮娥，素妝一夜相覺。"
    },
    {
        "ge_lyu_str": "平平仄仄仄仄仄仄平平仄平平仄仄平平平仄平平平仄平平仄仄平仄仄平平仄平仄仄平平仄仄平平仄平平仄平仄平仄仄仄平平仄仄仄平平仄仄平仄仄仄平平平平仄平仄平平仄仄仄平平平平仄仄仄平仄平平平仄仄仄平平仄仄平平仄平平仄平仄",
        "rhyme_pos": [
            2,
            10,
            22,
            34,
            47,
            62,
            75,
            90,
            103
        ],
        "yun_classify": {
            "0": [
                2,
                10,
                22,
                34,
                47,
                62,
                75,
                90,
                103
            ]
        },
        "ci_sep": [
            "长亭路",
            "望渭北　漠漠春天树",
            "殷勤别酒重斟　明日相思何处",
            "晴丝飏暖　芳草外　斜阳自南浦",
            "望孤帆　影接天涯　一江潮带愁去",
            "回首杜若汀洲　叹泛梗飘萍　乍散还聚",
            "满径残红春归后　犹有杨花乱舞",
            "怅金徽　梁尘暗锁　算谁是　知音堪共语",
            "尽天涯　梦断东风　䌽云鸾凤无侣"
        ],
        "ge_lyu_sep": [
            "平平仄韵",
            "仄仄仄读仄仄平平仄韵",
            "平平仄仄平平句平仄平平平仄韵",
            "平平仄仄句平仄仄读平平仄平仄韵",
            "仄平平读仄仄平平句仄平平仄平仄韵",
            "平仄仄仄平平句仄仄仄平平句仄仄平仄韵",
            "仄仄平平平平仄句平仄平平仄仄韵",
            "仄平平读平平仄仄句仄平仄读平平平仄仄韵",
            "仄平平读仄仄平平句仄平平仄平仄韵"
        ],
        "origin": "长亭路。望渭北、漠漠春天树。殷勤别酒重斟，明日相思何处。晴丝飏暖，芳草外、斜阳自南浦。望孤帆、影接天涯，一江潮带愁去。回首杜若汀洲，叹泛梗飘萍，乍散还聚。满径残红春归后，犹有杨花乱舞。怅金徽、梁尘暗锁，算谁是、知音堪共语。尽天涯、梦断东风，䌽云鸾凤无侣。",
        "origin_trad": "長亭路。望渭北、漠漠春天樹。殷勤別酒重斟，明日相思何處。晴絲颺暖，芳草外、斜陽自南浦。望孤帆、影接天涯，一江潮帶愁去。回首杜若汀洲，歎泛梗飄萍，乍散還聚。滿徑殘紅春歸後，猶有楊花亂舞。悵金徽、梁塵暗鎖，算誰是、知音堪共語。盡天涯、夢斷東風，綵雲鸞鳳無侶。"
    },
    {
        "ge_lyu_str": "仄平平仄平仄仄仄平仄平平平仄仄平平平仄仄仄平平平平仄平仄仄仄平仄仄仄平平平仄仄平仄平平仄平平仄平平仄仄仄仄平平仄平平平仄仄仄平平仄仄平平平仄仄仄平平仄仄平平平平仄平仄平平仄仄平仄仄仄平平仄平仄仄仄平平仄平平仄平平",
        "rhyme_pos": [
            2,
            10,
            22,
            35,
            48,
            54,
            63,
            77,
            92,
            105
        ],
        "yun_classify": {
            "0": [
                2,
                10,
                22,
                35,
                48,
                54,
                63,
                77,
                92,
                105
            ]
        },
        "ci_sep": [
            "去年时",
            "正愁绝　过却红杏飞",
            "沈吟杏子青时　追悔负好花枝",
            "今年又春到　傍小阑　日日数花期",
            "花有信　人却无凭　故教芳意迟迟",
            "及至待得融怡",
            "未攀条拈蕊　又叹春归",
            "怎得春如天不老　更教花与月相随",
            "都将命　拌与酬花　似岘山　落日客犹迷",
            "尽归路　拍手拦街　笑人沈醉如泥"
        ],
        "ge_lyu_sep": [
            "仄平平韵",
            "仄平仄读仄仄平仄平韵",
            "平平仄仄平平句平仄仄仄平平韵",
            "平平仄平仄句仄仄平读仄仄仄平平韵",
            "平仄仄读平仄平平句仄平平仄平平韵",
            "仄仄仄仄平平韵",
            "仄平平平仄句仄仄平平韵",
            "仄仄平平平仄仄句仄平平仄仄平平韵",
            "平平仄读平仄平平句仄仄平读仄仄仄平平韵",
            "仄平仄读仄仄平平句仄平平仄平平韵"
        ],
        "origin": "去年时。正愁绝、过却红杏飞。沈吟杏子青时，追悔负好花枝。今年又春到，傍小阑、日日数花期。花有信、人却无凭，故教芳意迟迟。及至待得融怡。未攀条拈蕊，又叹春归。怎得春如天不老，更教花与月相随。都将命、拌与酬花，似岘山、落日客犹迷。尽归路、拍手拦街，笑人沈醉如泥。",
        "origin_trad": "去年時。正愁絕、過却紅杏飛。沈吟杏子青時，追悔負好花枝。今年又春到，傍小闌、日日數花期。花有信、人却無憑，故教芳意遲遲。及至待得融怡。未攀條拈蕊，又歎春歸。怎得春如天不老，更教花與月相隨。都將命、拌與酬花，似峴山、落日客猶迷。儘歸路、拍手攔街，笑人沈醉如泥。"
    }
]