[
    {
        "ge_lyu_str": "平平仄平平平仄平中平中仄平平仄平平仄平中平仄平中平仄平中平中仄平平仄中平仄平",
        "rhyme_pos": [
            3,
            7,
            13,
            18,
            22,
            26,
            32,
            37
        ],
        "yun_classify": {
            "0": [
                3,
                7,
                13,
                18,
                22,
                26,
                32,
                37
            ]
        },
        "ci_sep": [
            "情高意真",
            "眉长鬓青",
            "小楼明月调筝",
            "写春风数声",
            "思君忆君",
            "魂牵梦萦",
            "翠绡香暖银屏",
            "更那堪酒醒"
        ],
        "ge_lyu_sep": [
            "平平仄平韵",
            "平平仄平韵",
            "中平中仄平平韵",
            "仄平平仄平韵",
            "中平仄平韵",
            "中平仄平韵",
            "中平中仄平平韵",
            "仄中平仄平韵"
        ],
        "origin": "情高意真。眉长鬓青。小楼明月调筝。写春风数声。思君忆君。魂牵梦萦。翠绡香暖银屏。更那堪酒醒。",
        "origin_trad": "情高意真。眉長鬢青。小樓明月調箏。寫春風數聲。思君憶君。魂牽夢縈。翠綃香暖銀屏。更那堪酒醒。"
    },
    {
        "ge_lyu_str": "中平仄仄平平仄仄仄平平仄仄平仄仄平平中仄平平中中中平仄平中仄中平仄仄仄平平仄平仄仄中中中仄",
        "rhyme_pos": [
            3,
            7,
            14,
            19,
            26,
            32,
            39,
            44
        ],
        "yun_classify": {
            "0": [
                3,
                7,
                14,
                19,
                26,
                32,
                39,
                44
            ]
        },
        "ci_sep": [
            "态浓意远",
            "眉颦笑浅",
            "薄罗衣窄絮风软",
            "鬓云欹翠卷",
            "南园花树春光暖",
            "香径里　榆钱满",
            "欲上鞦韆又惊懒",
            "且归休怕晚"
        ],
        "ge_lyu_sep": [
            "中平仄仄韵",
            "平平仄仄韵",
            "仄平平仄仄平仄韵",
            "仄平平中仄韵",
            "平平中中中平仄韵",
            "平中仄句中平仄韵",
            "仄仄平平仄平仄韵",
            "仄中中中仄韵"
        ],
        "origin": "态浓意远。眉颦笑浅。薄罗衣窄絮风软。鬓云欹翠卷。南园花树春光暖。香径里，榆钱满。欲上鞦韆又惊懒。且归休怕晚。",
        "origin_trad": "態濃意遠。眉顰笑淺。薄羅衣窄絮風軟。鬢雲欹翠卷。南園花樹春光暖。香徑裏，榆錢滿。欲上鞦韆又驚懶。且歸休怕晚。"
    },
    {
        "ge_lyu_str": "平平仄平仄仄平平中平中仄仄平平仄平平仄平中平中仄平平仄中平中仄中平仄仄平中仄仄平平仄平平仄平",
        "rhyme_pos": [
            3,
            7,
            14,
            19,
            26,
            33,
            40,
            45
        ],
        "yun_classify": {
            "0": [
                3,
                7,
                14,
                19,
                -26,
                -33,
                40,
                45
            ]
        },
        "ci_sep": [
            "钗分凤凰",
            "被剩鸳鸯",
            "锦笺遗恨爱花香",
            "写新愁半张",
            "晚妆楼阁空凝望",
            "旧游台榭添惆怅",
            "落花庭院又昏黄",
            "正离人断肠"
        ],
        "ge_lyu_sep": [
            "平平仄平韵",
            "仄仄平平韵",
            "中平中仄仄平平韵",
            "仄平平仄平韵",
            "中平中仄平平仄叶",
            "中平中仄中平仄叶",
            "仄平中仄仄平平韵",
            "仄平平仄平韵"
        ],
        "origin": "钗分凤凰。被剩鸳鸯。锦笺遗恨爱花香。写新愁半张。晚妆楼阁空凝望。旧游台榭添惆怅。落花庭院又昏黄。正离人断肠。",
        "origin_trad": "釵分鳳凰。被剩鴛鴦。錦箋遺恨愛花香。寫新愁半張。晚妝樓閣空凝望。舊遊臺榭添惆悵。落花庭院又昏黃。正離人斷腸。"
    }
]