[
    {
        "ge_lyu_str": "平平仄仄平平仄仄仄平平仄仄仄平中仄仄平平仄仄仄平平仄仄",
        "rhyme_pos": [
            6,
            12,
            26
        ],
        "yun_classify": {
            "0": [
                6,
                12,
                26
            ]
        },
        "ci_sep": [
            "西楼月落鸡声急",
            "夜浸疏香淅沥",
            "玉人酒渴嚼春冰　晓色入帘横宝瑟"
        ],
        "ge_lyu_sep": [
            "平平仄仄平平仄韵",
            "仄仄平平仄仄韵",
            "仄平中仄仄平平句仄仄仄平平仄仄韵"
        ],
        "origin": "西楼月落鸡声急。夜浸疏香淅沥。玉人酒渴嚼春冰，晓色入帘横宝瑟。",
        "origin_trad": "西樓月落雞聲急。夜浸疏香淅瀝。玉人酒渴嚼春冰，曉色入簾橫寶瑟。"
    },
    {
        "ge_lyu_str": "平平仄仄平平仄仄平平平仄仄仄平平仄仄平平仄仄平平平仄仄",
        "rhyme_pos": [
            6,
            12,
            26
        ],
        "yun_classify": {
            "0": [
                6,
                12,
                26
            ]
        },
        "ci_sep": [
            "瑶轩绮槛春风度",
            "柳垂烟　花带露",
            "半閒鸳被怯馀寒　燕子时来窥绣户"
        ],
        "ge_lyu_sep": [
            "平平仄仄平平仄韵",
            "仄平平句平仄仄韵",
            "仄平平仄仄平平句仄仄平平平仄仄韵"
        ],
        "origin": "瑶轩绮槛春风度。柳垂烟，花带露。半閒鸳被怯馀寒，燕子时来窥绣户。",
        "origin_trad": "瑤軒綺檻春風度。柳垂煙，花帶露。半閒鴛被怯餘寒，燕子時來窺繡戶。"
    }
]