[
    {
        "ge_lyu_str": "仄仄平平仄平平仄仄平中平中仄仄平平中仄中平中仄仄平平",
        "rhyme_pos": [
            9,
            16,
            25
        ],
        "yun_classify": {
            "0": [
                9,
                16,
                25
            ]
        },
        "ci_sep": [
            "柳色遮楼暗　桐花落砌香",
            "画堂开处晚风凉",
            "高卷水晶帘额衬斜阳"
        ],
        "ge_lyu_sep": [
            "仄仄平平仄句平平仄仄平韵",
            "中平中仄仄平平韵",
            "中仄中平中仄仄平平韵"
        ],
        "origin": "柳色遮楼暗，桐花落砌香。画堂开处晚风凉。高卷水晶帘额衬斜阳。",
        "origin_trad": "柳色遮樓暗，桐花落砌香。畫堂開處晚風凉。高卷水晶簾額襯斜陽。"
    },
    {
        "ge_lyu_str": "仄仄平平仄平平仄仄平中平中仄仄平平中仄中平中仄仄平平仄仄平平仄平平仄仄平中平中仄仄平平中仄中平中仄仄平平",
        "rhyme_pos": [
            9,
            16,
            25,
            35,
            42,
            51
        ],
        "yun_classify": {
            "0": [
                9,
                16,
                25,
                35,
                42,
                51
            ]
        },
        "ci_sep": [
            "驿路侵斜月　溪桥度晓霜",
            "短篱残菊一枝黄",
            "正是乱山深处过重阳",
            "旅枕原无梦　寒更每自长",
            "只言江左好风光",
            "不道中原归思转凄凉"
        ],
        "ge_lyu_sep": [
            "仄仄平平仄句平平仄仄平韵",
            "中平中仄仄平平韵",
            "中仄中平中仄仄平平韵",
            "仄仄平平仄句平平仄仄平韵",
            "中平中仄仄平平韵",
            "中仄中平中仄仄平平韵"
        ],
        "origin": "驿路侵斜月，溪桥度晓霜。短篱残菊一枝黄。正是乱山深处过重阳。旅枕原无梦，寒更每自长。只言江左好风光。不道中原归思转凄凉。",
        "origin_trad": "驛路侵斜月，溪橋度曉霜。短籬殘菊一枝黃。正是亂山深處過重陽。旅枕原無夢，寒更每自長。只言江左好風光。不道中原歸思轉凄凉。"
    }
]