[
    {
        "ge_lyu_str": "平平仄仄仄仄仄中平中中平仄中仄平平中仄仄平平仄中平中仄平平仄仄平平中平平仄仄平平仄中平中仄仄平平仄仄中中平平仄仄仄中中平中中中平仄中仄平平中仄仄平平仄中平中仄平平仄仄平平中仄平仄仄平平仄中平中仄仄平平仄",
        "rhyme_pos": [
            3,
            12,
            22,
            36,
            48,
            55,
            64,
            74,
            88,
            100
        ],
        "yun_classify": {
            "0": [
                3,
                12,
                22,
                36,
                48,
                55,
                64,
                74,
                88,
                100
            ]
        },
        "ci_sep": [
            "登临送目",
            "正故国晚秋　天气初肃",
            "千里澄江似练　翠峰如簇",
            "征帆去棹残阳里　背西风　酒旗斜矗",
            "彩舟云淡　星河鹭起　画图难足",
            "念往昔　繁华竞逐",
            "叹门外楼头　悲恨相续",
            "千古凭高对此　漫嗟荣辱",
            "六朝旧事随流水　但寒烟芳草凝绿",
            "至今商女　时时犹唱　后庭遗曲"
        ],
        "ge_lyu_sep": [
            "平平仄仄韵",
            "仄仄仄中平句中中平仄韵",
            "中仄平平中仄句仄平平仄韵",
            "中平中仄平平仄句仄平平读中平平仄韵",
            "仄平平仄句中平中仄句仄平平仄韵",
            "仄中中读平平仄仄韵",
            "仄中中平中句中中平仄韵",
            "中仄平平中仄句仄平平仄韵",
            "中平中仄平平仄句仄平平中仄平仄韵",
            "仄平平仄句中平中仄句仄平平仄韵"
        ],
        "origin": "登临送目。正故国晚秋，天气初肃。千里澄江似练，翠峰如簇。征帆去棹残阳里，背西风、酒旗斜矗。彩舟云淡，星河鹭起，画图难足。念往昔、繁华竞逐。叹门外楼头，悲恨相续。千古凭高对此，漫嗟荣辱。六朝旧事随流水，但寒烟芳草凝绿。至今商女，时时犹唱，后庭遗曲。",
        "origin_trad": "登臨送目。正故國晚秋，天氣初肅。千里澄江似練，翠峰如簇。征帆去棹殘陽裏，背西風、酒旗斜矗。彩舟雲淡，星河鷺起，畫圖難足。念往昔、繁華競逐。嘆門外樓頭，悲恨相續。千古凭高對此，漫嗟榮辱。六朝舊事隨流水，但寒烟芳草凝綠。至今商女，時時猶唱，後庭遺曲。"
    }
]